mkdocs_code_runner/__init__.py
mkdocs_code_runner/lib.py
mkdocs_code_runner/plugin.py
mkdocs_code_runner/py.typed
mkdocs_code_runner-0.0.1.dist-info/entry_points.txt
mkdocs_code_runner-0.0.1.dist-info/LICENSE.md
mkdocs_code_runner-0.0.1.dist-info/WHEEL
mkdocs_code_runner-0.0.1.dist-info/METADATA
mkdocs_code_runner-0.0.1.dist-info/RECORD
