Metadata-Version: 2.1
Name: mkdocs-code-runner
Version: 0.0.1
Summary: Mkdocs plugin for converting JavaScript code into runnable scripts.
Home-page: https://github.com/wolfgangwazzlestrauss/mkdocs-code-runner
License: MIT
Author: Macklan Weinstein
Author-email: wolfgangwazzlestrauss@gmail.com
Requires-Python: >=3.6,<4.0
Classifier: License :: OSI Approved :: MIT License
Classifier: Programming Language :: Python :: 3
Classifier: Programming Language :: Python :: 3.6
Classifier: Programming Language :: Python :: 3.7
Classifier: Programming Language :: Python :: 3.8
Requires-Dist: beautifulsoup4 (>=4.8.2,<5.0.0)
Requires-Dist: mkdocs (>=1.1,<2.0)
